CHANGES.txt
MANIFEST.in
README.txt
setup.py
stackmob-cli
client/__init__.py
stackmob_cli.egg-info/PKG-INFO
stackmob_cli.egg-info/SOURCES.txt
stackmob_cli.egg-info/dependency_links.txt
stackmob_cli.egg-info/requires.txt
stackmob_cli.egg-info/top_level.txt
util/__init__.py