Metadata-Version: 1.0
Name: stackmob-cli
Version: 0.1.1
Summary: A command line interface for accessing your StackMob API
Home-page: http://github.com/stackmob/stackmob-cli
Author: Aaron Schlesinger
Author-email: aaron@stackmob.com
License: UNKNOWN
Platform: UNKNOWN
